dataset_sh/__init__.py
dataset_sh/cli.py
dataset_sh/constants.py
dataset_sh/core.py
dataset_sh/io.py
dataset_sh/models.py
dataset_sh/clients/__init__.py
dataset_sh/clients/common.py
dataset_sh/clients/locator.py
dataset_sh/clients/obj.py
dataset_sh/clients/remote.py
dataset_sh/dependency/__init__.py
dataset_sh/dependency/model.py
dataset_sh/dependency/parser.py
dataset_sh/fileserver/__init__.py
dataset_sh/fileserver/client.py
dataset_sh/fileserver/sign.py
dataset_sh/fileserver/utils.py
dataset_sh/multipart/__init__.py
dataset_sh/multipart/download.py
dataset_sh/multipart/multipart.py
dataset_sh/multipart/upload.py
dataset_sh/remote_utils/__init__.py
dataset_sh/remote_utils/profile.py
dataset_sh/server/__init__.py
dataset_sh/server/app.py
dataset_sh/server/app_cli.py
dataset_sh/server/auth.py
dataset_sh/server/config.py
dataset_sh/server/config_cli.py
dataset_sh/server/constants.py
dataset_sh/server/core.py
dataset_sh/server/daemon.py
dataset_sh/server/project_file_manager.py
dataset_sh/server/utils.py
dataset_sh/server/assets/__init__.py
dataset_sh/server/assets/app-ui.frontend
dataset_sh/subcmds/__init__.py
dataset_sh/subcmds/author.py
dataset_sh/subcmds/file.py
dataset_sh/subcmds/gui.py
dataset_sh/subcmds/local.py
dataset_sh/subcmds/profile.py
dataset_sh/subcmds/project.py
dataset_sh/subcmds/remote.py
dataset_sh/typing/__init__.py
dataset_sh/typing/codegen.py
dataset_sh/typing/constants.py
dataset_sh/typing/core.py
dataset_sh/typing/schema_builder.py
dataset_sh/utils/__init__.py
dataset_sh/utils/author.py
dataset_sh/utils/dump.py
dataset_sh/utils/files.py
dataset_sh/utils/help.py
dataset_sh/utils/misc.py
dataset_sh/utils/pandas.py
dataset_sh/utils/sample.py
dataset_sh/utils/test_utils.py
dataset_sh/utils/usage/__init__.py
dataset_sh/utils/usage/read_data_codegen.py
dataset_sh-0.0.39.dist-info/METADATA
dataset_sh-0.0.39.dist-info/WHEEL
dataset_sh-0.0.39.dist-info/entry_points.txt
dataset_sh-0.0.39.dist-info/RECORD
