Metadata-Version: 2.4
Name: dataset.sh
Version: 0.0.39
Summary: Dataset.sh: help you create, share, and use dataset
Project-URL: Homepage, https://dataset.sh
Project-URL: Bug Tracker, https://github.com/dataset-sh/dataset-sh
Author-email: Hao Wu <haowu@dataset.sh>
License: MIT License
Classifier: License :: OSI Approved :: MIT License
Classifier: Operating System :: OS Independent
Classifier: Programming Language :: Python :: 3
Classifier: Topic :: Scientific/Engineering :: Artificial Intelligence
Classifier: Topic :: Scientific/Engineering :: Information Analysis
Requires-Python: >=3.9
Requires-Dist: click~=8.0
Requires-Dist: flask~=3.0
Requires-Dist: head-switcher~=0.0.2
Requires-Dist: pydantic>=2.9.2
Requires-Dist: pyjwt~=2.0
Requires-Dist: requests~=2.0
Requires-Dist: tqdm~=4.0
Requires-Dist: typelang>=0.0.1
Provides-Extra: all
Requires-Dist: flask~=3.0.1; extra == 'all'
Requires-Dist: head-switcher>=0.0.1; extra == 'all'
Requires-Dist: pyjwt~=2.8.0; extra == 'all'
Provides-Extra: server
Requires-Dist: flask~=3.0.1; extra == 'server'
Requires-Dist: head-switcher>=0.0.1; extra == 'server'
Requires-Dist: pyjwt~=2.8.0; extra == 'server'
Provides-Extra: tests
Requires-Dist: build~=1.1.1; extra == 'tests'
Requires-Dist: coverage~=7.3.2; extra == 'tests'
Requires-Dist: pkginfo~=1.10.0; extra == 'tests'
Requires-Dist: pytest~=8.3.3; extra == 'tests'
Requires-Dist: twine~=5.0.0; extra == 'tests'
